gitlab_mr_note/.gitlab-ci.yml
gitlab_mr_note/__init__.py
gitlab_mr_note/cli.py
gitlab_mr_note/config.py
gitlab_mr_note/core.py
gitlab_mr_note-1.0.0.dist-info/METADATA
gitlab_mr_note-1.0.0.dist-info/WHEEL
gitlab_mr_note-1.0.0.dist-info/entry_points.txt
gitlab_mr_note-1.0.0.dist-info/RECORD
