Metadata-Version: 2.1
Name: gitlab-mr-note
Version: 1.0.0
Summary: 
Author: Irene
Author-email: irene@wn.com
Requires-Python: >=3.7,<4.0
Classifier: Programming Language :: Python :: 3
Classifier: Programming Language :: Python :: 3.7
Classifier: Programming Language :: Python :: 3.8
Classifier: Programming Language :: Python :: 3.9
Classifier: Programming Language :: Python :: 3.10
Classifier: Programming Language :: Python :: 3.11
Requires-Dist: click (>=8.1.3,<9.0.0)
Requires-Dist: python-gitlab (>=3.12.0,<4.0.0)
